spacetrack/__init__.py
spacetrack/aio.py
spacetrack/base.py
spacetrack/operators.py
spacetrack-1.3.1.dist-info/LICENSE.txt
spacetrack-1.3.1.dist-info/METADATA
spacetrack-1.3.1.dist-info/WHEEL
spacetrack-1.3.1.dist-info/top_level.txt
spacetrack-1.3.1.dist-info/RECORD
