Metadata-Version: 2.1
Name: spacetrack
Version: 1.3.1
Summary: Python client for space-track.org
Author-email: Frazer McLean <frazer@frazermclean.co.uk>
License: MIT
Project-URL: Repository, https://github.com/python-astrodynamics/spacetrack
Project-URL: Documentation, https://spacetrack.readthedocs.io
Classifier: Development Status :: 4 - Beta
Classifier: License :: OSI Approved :: MIT License
Classifier: Programming Language :: Python :: 3 :: Only
Classifier: Programming Language :: Python :: 3.8
Classifier: Programming Language :: Python :: 3.9
Classifier: Programming Language :: Python :: 3.10
Classifier: Programming Language :: Python :: 3.11
Classifier: Programming Language :: Python :: 3.12
Requires-Python: >=3.8
License-File: LICENSE.txt
Requires-Dist: httpx
Requires-Dist: logbook>=0.12.3
Requires-Dist: python-dateutil; python_version < "3.11"
Requires-Dist: represent>=1.4.0
Requires-Dist: rush
Requires-Dist: sniffio
Provides-Extra: test
Requires-Dist: pytest-asyncio; extra == "test"
Requires-Dist: pytest-trio; extra == "test"
Requires-Dist: pytest>=6.0; extra == "test"
Requires-Dist: respx; extra == "test"
Provides-Extra: docstest
Requires-Dist: doc8; extra == "docstest"
Requires-Dist: parver; extra == "docstest"
Requires-Dist: sphinx; extra == "docstest"
Requires-Dist: furo; extra == "docstest"
Provides-Extra: pep8test
Requires-Dist: flake8; extra == "pep8test"
Requires-Dist: flake8-future-import; extra == "pep8test"
Requires-Dist: pep8-naming; extra == "pep8test"
